zsx_facile_heatmap.py
zsx_facile_heatmap-2.0.0.dist-info/METADATA
zsx_facile_heatmap-2.0.0.dist-info/WHEEL
zsx_facile_heatmap-2.0.0.dist-info/top_level.txt
zsx_facile_heatmap-2.0.0.dist-info/RECORD
