Metadata-Version: 2.1
Name: zsx_facile_heatmap
Version: 2.0.0
Summary: Facile & flexible heatmap plotting
Author-email: Zhang Senxin <sxzhang997@qq.com>
Project-URL: Homepage, https://github.com/ZhangSenxin/zsx_some_tools
Project-URL: Bug Tracker, https://github.com/ZhangSenxin/zsx_some_tools/issues
Classifier: Programming Language :: Python :: 3
Classifier: License :: OSI Approved :: MIT License
Classifier: Operating System :: OS Independent
Requires-Python: >=3.6
